py_conway/__init__.py
py_conway/game.py
py_conway/helpers.py
py_conway/threaded_game.py
py_conway-0.6.0.dist-info/LICENSE
py_conway-0.6.0.dist-info/METADATA
py_conway-0.6.0.dist-info/WHEEL
py_conway-0.6.0.dist-info/top_level.txt
py_conway-0.6.0.dist-info/RECORD
