Metadata-Version: 2.1
Name: py-conway
Version: 0.6.0
Summary: TDD-style implementation of Conway's Game of Life in Python
Home-page: https://github.com/bsatrom/py-conway
Author: Brandon Satrom
Author-email: bsatrom@gmail.com
License: UNKNOWN
Platform: UNKNOWN
Classifier: Programming Language :: Python
Classifier: Programming Language :: Python :: 3.5
Classifier: Programming Language :: Python :: 3.6
Classifier: Programming Language :: Python :: 3.7
Classifier: Programming Language :: Python :: 3.8
Classifier: License :: OSI Approved :: Apache Software License
Classifier: Operating System :: OS Independent
Classifier: Intended Audience :: Developers
Classifier: Natural Language :: English
Requires-Python: >=3.5
